opensearch_optic-2.0.0.dist-info/licenses/LICENSE.txt
optic/__init__.py
optic/__main__.py
optic/cli.py
optic/alias/__init__.py
optic/alias/alias.py
optic/alias/alias_service.py
optic/cluster/__init__.py
optic/cluster/cluster.py
optic/cluster/cluster_service.py
optic/common/__init__.py
optic/common/api.py
optic/common/config.py
optic/common/exceptions.py
optic/common/helpers.py
optic/common/optic_color.py
optic/index/__init__.py
optic/index/index.py
optic/index/index_service.py
optic/initialize/__init__.py
optic/initialize/initialize_service.py
opensearch_optic-2.0.0.dist-info/METADATA
opensearch_optic-2.0.0.dist-info/WHEEL
opensearch_optic-2.0.0.dist-info/entry_points.txt
opensearch_optic-2.0.0.dist-info/top_level.txt
opensearch_optic-2.0.0.dist-info/RECORD
