Metadata-Version: 2.4
Name: opensearch-optic
Version: 2.0.0
Summary: Opensearch Tools for Indices and Clusters
Author-email: Seth Lippman <seth.lippman@oracle.com>, Franklin Freitas <franklin.freitas.de.sousa@oracle.com>, Brandon Cisneros <brandon.cisneros@oracle.com>
Project-URL: Homepage, https://github.com/oracle/optic
Project-URL: Issues, https://github.com/oracle/optic/issues
Classifier: Programming Language :: Python :: 3
Classifier: License :: OSI Approved :: MIT License
Classifier: Operating System :: OS Independent
Requires-Python: >=3.12
License-File: LICENSE.txt
Requires-Dist: click==8.1.8
Requires-Dist: python-dateutil==2.9.0.post0
Requires-Dist: PyYAML==6.0.2
Requires-Dist: requests==2.32.4
Requires-Dist: terminaltables==3.1.10
Requires-Dist: urllib3==2.5.0
Provides-Extra: dev
Requires-Dist: certifi==2024.6.2; extra == "dev"
Requires-Dist: charset-normalizer==3.3.2; extra == "dev"
Requires-Dist: idna==3.7; extra == "dev"
Requires-Dist: setuptools; extra == "dev"
Requires-Dist: pytest; extra == "dev"
Requires-Dist: pytest-cov; extra == "dev"
Requires-Dist: black; extra == "dev"
Requires-Dist: flake8; extra == "dev"
Requires-Dist: flake8-bandit; extra == "dev"
Requires-Dist: flake8-bugbear; extra == "dev"
Requires-Dist: flake8-builtins; extra == "dev"
Requires-Dist: flake8-comprehensions; extra == "dev"
Requires-Dist: flake8-eradicate; extra == "dev"
Requires-Dist: flake8-implicit-str-concat; extra == "dev"
Requires-Dist: flake8-per-file-ignores; extra == "dev"
Requires-Dist: flake8-print; extra == "dev"
Requires-Dist: isort; extra == "dev"
Requires-Dist: pep8-naming; extra == "dev"
Requires-Dist: pre-commit; extra == "dev"
Requires-Dist: pytest-mock; extra == "dev"
Dynamic: license-file
